robotpy_halsim_lowfi-2020.1.2.0.data/purelib/halsim_lowfi/__init__.py
robotpy_halsim_lowfi-2020.1.2.0.data/purelib/halsim_lowfi/_init_halsim_lowfi.py
robotpy_halsim_lowfi-2020.1.2.0.data/purelib/halsim_lowfi/main.py
robotpy_halsim_lowfi-2020.1.2.0.data/purelib/halsim_lowfi/pkgcfg.py
robotpy_halsim_lowfi-2020.1.2.0.data/purelib/halsim_lowfi/version.py
robotpy_halsim_lowfi-2020.1.2.0.data/purelib/halsim_lowfi/include/HALSimLowFi.h
robotpy_halsim_lowfi-2020.1.2.0.data/purelib/halsim_lowfi/include/LICENSE.txt
robotpy_halsim_lowfi-2020.1.2.0.data/purelib/halsim_lowfi/include/NTProvider_Analog.h
robotpy_halsim_lowfi-2020.1.2.0.data/purelib/halsim_lowfi/include/NTProvider_DIO.h
robotpy_halsim_lowfi-2020.1.2.0.data/purelib/halsim_lowfi/include/NTProvider_DriverStation.h
robotpy_halsim_lowfi-2020.1.2.0.data/purelib/halsim_lowfi/include/NTProvider_Encoder.h
robotpy_halsim_lowfi-2020.1.2.0.data/purelib/halsim_lowfi/include/NTProvider_PWM.h
robotpy_halsim_lowfi-2020.1.2.0.data/purelib/halsim_lowfi/include/NTProvider_Relay.h
robotpy_halsim_lowfi-2020.1.2.0.data/purelib/halsim_lowfi/include/NTProvider_RoboRIO.h
robotpy_halsim_lowfi-2020.1.2.0.data/purelib/halsim_lowfi/include/NTProvider_dPWM.h
robotpy_halsim_lowfi-2020.1.2.0.data/purelib/halsim_lowfi/include/ThirdPartyNotices.txt
robotpy_halsim_lowfi-2020.1.2.0.data/purelib/halsim_lowfi/lib/halsim_lowfi.dll
robotpy_halsim_lowfi-2020.1.2.0.dist-info/METADATA
robotpy_halsim_lowfi-2020.1.2.0.dist-info/WHEEL
robotpy_halsim_lowfi-2020.1.2.0.dist-info/entry_points.txt
robotpy_halsim_lowfi-2020.1.2.0.dist-info/top_level.txt
robotpy_halsim_lowfi-2020.1.2.0.dist-info/RECORD
