Metadata-Version: 2.1
Name: robotpy-halsim-lowfi
Version: 2020.1.2.0
Summary: WPILib command framework
Home-page: https://github.com/robotpy/robotpy-halsim-lowfi
Author: RobotPy Development Team
Author-email: robotpy@googlegroups.com
License: BSD-3-Clause
Platform: UNKNOWN
Requires-Python: >=3.6
